ManagerTk.py
ManagerTk-0.3.dist-info/License.txt
ManagerTk-0.3.dist-info/METADATA
ManagerTk-0.3.dist-info/WHEEL
ManagerTk-0.3.dist-info/top_level.txt
ManagerTk-0.3.dist-info/RECORD
